herberta/__init__.py
herberta/embedding.py
herberta-0.1.0.dist-info/LICENSE
herberta-0.1.0.dist-info/METADATA
herberta-0.1.0.dist-info/WHEEL
herberta-0.1.0.dist-info/top_level.txt
herberta-0.1.0.dist-info/RECORD
