Metadata-Version: 2.1
Name: herberta
Version: 0.1.0
Summary: A Python package for converting texts to embeddings using pretrained models.
Home-page: https://github.com/15392778677/herberta
Author: XiaoEn
Author-email: 1958944515@qq.com
Classifier: Programming Language :: Python :: 3
Classifier: License :: OSI Approved :: MIT License
Classifier: Operating System :: OS Independent
Requires-Python: >=3.10
License-File: LICENSE
Requires-Dist: torch >=1.9
Requires-Dist: transformers >=4.0
